{
  "title": "بذر الإيمان في القلب الصغير — بطاقات",
  "cards": [
    {
      "front": "إزاي يبدأ المنهج النبوي في التربية؟",
      "back": "يبدأ بالعقيدة | لا تُعلَّم بالمحاضرات بل بالبيئة والتكرار والقدوة | تُغرَس في الوجدان قبل العقل"
    },
    {
      "front": "الطفل 0-3 بيفهم معنى الله؟",
      "back": "لا يفهم المعنى بعد | لكنه يسمع اسمه في كل موقف فيألفه | التكرار يبني مفردات إيمانية في عقله"
    },
    {
      "front": "إزاي تربط اللحظات الجميلة باسم الله؟",
      "back": "'بسم الله' عند الأكل والتغيير | 'الحمد لله' عند الاستيقاظ | 'ماشاء الله' عند رؤية الجميل"
    },
    {
      "front": "ليه نكرّر ذكر الله أمام الرضيع؟",
      "back": "التكرار يبني ألفة قبل الفهم | يربط الفرح والطمأنينة بالله | الإيمان يرسخ في الوجدان مبكراً"
    },
    {
      "front": "تطبيق عملي لبذر الإيمان؟",
      "back": "قل 'بسم الله' بصوت مسموع عند كل رعاية | ابدأ صباحه بـ'الحمد لله الذي أحيانا' | أشر للجميل وقل 'ماشاء الله'"
    }
  ]
}
