{
  "title": "الصحة النفسية في الجامعة/العمل — بطاقات",
  "cards": [
    {
      "front": "إيه ضغوط الانتقال للجامعة/العمل؟",
      "back": "الغربة والبُعد عن الأهل | ضغط الأداء والقرارات المالية | علاقات جديدة ومسؤولية مستقلة"
    },
    {
      "front": "أساس الاتزان النفسي عند الاستقلال؟",
      "back": "روتين ثابت: نوم وحركة وغذاء | أساس كيميائي لصحة الدماغ | الانتظام يحمي من الانهيار"
    },
    {
      "front": "مين شبكة الدعم في هذه المرحلة؟",
      "back": "صديق موثوق ومرشد أكاديمي | مستشار نفسي في الجامعة | خط ساخن (937) محفوظ"
    },
    {
      "front": "إيه 'علامات التحذير الشخصية'؟",
      "back": "اكتب علاماتك الخاصة (عزلة، أرق، فقدان شغف) | راقبها أسبوعياً | تدخّل مبكراً قبل التفاقم"
    },
    {
      "front": "إيه خطة الطوارئ النفسية؟",
      "back": "أرقام 937/112 | صديق طوارئ تثق به | طبيب نفسي تعرف رقمه — الاستقلال مسؤولية صحتك"
    }
  ]
}
