{
  "id": "isl-20cd665c",
  "domain": "islamic_parenting",
  "source_file": "Alukah_Rights_of_Children.pdf",
  "title": "تعليم الأطفال الصلاة والتربية الدينية",
  "language": "ar",
  "age_group": "4-6",
  "behavior_type": "تربية دينية",
  "intervention_type": "إرشادي",
  "severity": "خفيف",
  "reference_type": "كتاب_تربوي",
  "reference_info": "حقوق الأولاد على الوالدين - عماد عبدالعظيم (الألوكة)",
  "text_original": "ذ ذ ُ َ َ ﴿ :أرق ,رادلا ؾخدف فؾهأ كلإ عجر اذنف ,افرص ؿهاقكد ىِٰإ ميجيع ندٍتّ لَو .)11ص( »دمًقمًا ةحمٞمّمٟ مذ دبمٙمًا ةتمٗمً« (1) .ـسمط دمٜسمس همػمهو ،)71( »دهزمًا« مذ دواد قمسأ فمضرمظأ (2) ــــــــــــــــــــــــــــــــــــــــــــــــــــــــــــــــــــــــــــــــــــ نيدلاىلا ىلع دلاولأا قىقح ــــــــــــــــــــ بّ ّ ر َ ق ُ ز ۡ رو َ ِّۚ يِػ ً ۡ ٓ ُ ِ َ ِ خ ف ۡ َ لنِّ اي َ نّ ۡ لَّ ُ ٱ ِةٔ ٰ ي َ لۡ َ ٱ َ ةر َ ْ ۡ ز َ ً ۡ ٓ ُ ِ ۡ ٌِ ّ ا ج ٗ ٰو َ ز ۡ أ ٓ ۦِِّة اِ َ ػ ۡ خ ذ ٌ َ اٌ َ َ ُ ُ ۡ َ ُ ۡ ذ ٗ ۡ َ ُ َ ۡ َ َ َ ۡ َ َ ۡ َ ۡ َ ٰ َ ذ َ َ ۡ َ ۡ ُ ۡ َ ٰ َ ۡ َ َ ۗمكزرُ َ نَّ ۡا كز ر مي س ٔ ن لَ ۡآييغ بِ طغٱو ِةٔيػلٱِة ميْأ رمأو ١٣١ ق بخو .)1(للها ؿؽؿحر ةلاصلا ةلاصلا :لاق ﴾ٰ َ ۡ ذ ُ َ ٰ َ ۡ َ ىٔلخيِل ثتِلعىٱو ؿؾعي للهاو ,ؼثاقلا مايأ في لبأ كؾط تؾخد :ؾبـح ـب دؿحأ ـب حلاص لاق دق ,افقؾط سؾجي دبل فل ناك دقو ,رصعلا ةلاصل جرخ دقو ,ـحك ةلاح يأ في ابأ اي لـغؾب فقف اذإو ,دغاك باتك فتحت اذنف لؾب دق كتح ةرقثك نقـس فقؾط تتأ ةعبرلب ؽقلإ تفجو دقو ,ـيدلا ـم ؽقؾط امو ,ؼقضلا ـم فقف تكأ ام",
  "text_simplified": "يجب على الأهل تعليم الأطفال الصلاة وتعويدهم عليها منذ الصغر. كما ينبغي أن يكون الوالدان قدوة حسنة لأبنائهم في أداء العبادات. النص يشير إلى أهمية تربية الأطفال على القيم الدينية والأخلاقية.",
  "labels": [
    "تربية",
    "صلاة",
    "قدوة",
    "أطفال",
    "دين"
  ],
  "created_at": "2026-06-21T10:30:31Z",
  "updated_at": "2026-06-21T10:30:31Z",
  "version": "1.0.0",
  "source_meta": {
    "source_title": "Alukah_Rights_of_Children",
    "source_author": ""
  }
}