{
  "id": "med-0b39e5a8",
  "domain": "medical",
  "source_file": "SFDA_Healthy_Nutrition_Guide.pdf",
  "title": "نشاط بدني وتغذية صحية للأطفال",
  "language": "ar",
  "age_group": "7-9",
  "behavior_type": "نشاط بدني وتغذية صحية",
  "intervention_type": "إرشادي",
  "severity": "خفيف",
  "reference_type": "تقرير_طبي",
  "reference_info": "دليل التغذية الصحية - هيئة الغذاء والدواء السعودية",
  "text_original": "ﺔـــﺳرﺎﻤﻣو ﻢﻟﻼـــﺴﻟا مﺪﺨﺘـــﺳا :ﻞﺜﻣ) ةﺮـــﻴﺼﻗ تﺎﻓﺎـــﺴﻣ ﻊﻄﻘﻟ ﺔﺟﺎﺤﻟا ﺪﻨﻋ ﻲﻧﺪﺒﻟا طﺎـــﺸﻨﻟا سرﺎـــﻣ .ﺔﻛﺮﺤﺘﻤﻟا ﻢﻟﻼﺴﻟا ﺔـــﺟارﺪﻟا بﻮـــﻛر وأ ﻲـــﺸﻤﻟا سرﺎـــﻣ (ﺐـــﻳﺮﻗ ﺪﻨﻋ Âﻄﻴـــﺸﻧ دﺮـــﻔﻟا ﺮـــﺒﺘﻌﻳ ﺪﻨﻋ Âﻄﻴـــﺸﻧ ﻞﻔﻄﻟا ﺮـــﺒﺘﻌﻳ ﺔﻴﻧﺪﺒﻟا ﺔﻄـــﺸﻧ´ا ﺔـــﺳرﺎﻤﻣ ﺔﻴﻧﺪﺒﻟا ﺔﻄـــﺸﻧ´ا ﺔـــﺳرﺎﻤﻣ ﺔﻘﻴﻗد 30 ةﺪـــﻤﻟ ﺔﻄـــﺳﻮﺘﻣ ةﺪﻳﺪـــﺸﻟا ﻰـــﻟإ ﺔﻄـــﺳﻮﺘﻤﻟا ﻰـــﻠﻋ ﺔـــﻴﺋاﻮﻬﻟا ﺔـــﺟارﺪﻟا .ﺔــــــﻠﺴﻟا ةﺮـــــﻛ .ﻞــــﺒﺤﻟﺎﺑ ﺰـــﻔﻘﻟا .ﺐﻌﺘﻟﺎﺑ رﻮﻌﺸﻟاو فﺎﻔﺠﻟا :ءﺎـــــــــﻤﻟا ﻦﻣ رﺬﺤﻟا صﻮـــﺼﺨﻟا ﻪﺟو ﻰـــﻠﻋ ﻦـــﺴﻟا رﺎﺒﻛ ﻰﻠﻋ ﺐﺠﻳ ﻊﻣ ﺶﻄﻌﻟﺎﺑ رﻮﻌـــﺸﻟا ﺪـــﻘﻔﻳ نﺎـــﺴﻧœا ن´ فﺎـــﻔﺠﻟا بوﺮــﺸﻣ ﻞــﻀﻓأ ءﺎـــﻤﻟا ﺔﺳرﺎﻤﻣ وأ ﺲﻘﻄﻟا ةراﺮﺣ عﺎﻔﺗرا ﺐﺒـــﺴﺑ ﺪﻳﺪﺸﻟا قﺮﻌﺘﻟا ﺪﻨﻋ ﻞﺋاﻮﺴﻟا كﻼﻬﺘـــﺳا ﻲﻓ ةدﺎﻳز ﻰﻟإ دﺮﻔﻟا جﺎﺘﺤﻳ .وﺎﻛﺎﻜﻟاو يﺎـــﺸﻟاو ةﻮـــﻬﻘﻟا ﻞﺜﻣ تﺎﺑوﺮـــﺸﻤﻟاو ﺔﻳزﺎﻐﻟا تﺎﺑوﺮـــﺸﻤﻟا ﻲﻓ ﺔﻓﺎﻀﻣ ةدﺎﻤﻛ ﻞﻤﻌﺘـــﺴﺗو هﺎﻧدأ لوﺪﺠﻟا ﺢﺿﻮﻳ .ﻦﻫﺪﻟا ةﺪﺑزو رﺎﻄﻓ©ا ﻦـــــﻣ ﺔﻳﺎﻗﻮﻠﻟ ﺦﺒﻄﻟ ﺔـــﺼﻠﺻ داﺪﻋإ ﺪـــﻨﻋ ﻪـــﻛاﻮﻔﻟا لﺎﻤﻌﺘـــﺳا ﻰﻠﻋ ﺔﺤﻠﻤﻤﻟا ﻊـــﺿو ﺐﻨﺠﺗ تﻮﺘﻟاو حﺎﻔﺘﻟا ﺔـــﺼﻠﺻ :ﻞﺜﻣ ﻦﺟاوﺪﻟا وأ مﻮـــﺤﻠﻟا .مﺎﻌﻄﻟا ﺔﻟوﺎﻃ ﻞﻔﻠﻔﻟاو ﻞﺨﻟاو نﻮﻤﻴﻠﻟاو ﻞﺑاﻮﺘﻟا ـﺑ ﺢﻠﻤﻟا لاﺪﺒﺘﺳا ءﺎﻨﺛأ ﺢﻠﻤﻟا ماﺪﺨﺘـــﺳا ﻞﻠّﻗ ءاﺬﻐﻟا ﻲـــﻓ ﻪﺘﻴﻤﻛ ﻞـــﻴﻠﻘﺗ ﻖـــﻳﺮﻃ ﻦـــﻋ ﺢـــﻠﻤﻟا ردوﺎﺑ ﺞﻨﻛﺎﺑ مﻮﻳدﻮﺼﻟا تاﺮﺘﻧ مﻮﻳدﻮﺼﻟا تاوﺰﻨﺑ ،ﻞـــﺴﻌﻟاو ،ﻪﻛاﻮﻔﻟا :ﻞـــﺜﻣ ،ﺔـــﻳﺬﻏ(cid:23)ا ﻲـــﻓ ﺎﻴًﻌﻴﺒﻃ يﺮﻜﺴﻟﺎﺑ ﺔﺑﺎﺻ©ا .ﺐﻴﻠﺤﻟاو ﺐﻠﻘﻟا ضاﺮﻣأو .ﺐﻠﻘﻟا ضاﺮﻣأو ،مﺪﻟﺎﺑ نﻮﻫﺪﻟا عﺎﻔﺗراو ،يﺮﻜﺴﻟﺎﺑ ﺔﺑﺎﺻœا ﺮﻄﺧ ةدﺎﻳزو ،نزﻮﻟا ةدﺎﻳﺰﺑ تﺎﺑوﺮـــﺸﻣو ﺔﻳزﺎﻐﻟا تﺎﺑوﺮـــﺸﻤﻟا ﻦـــﻋ ﺪـــﻌﺘﺑا باﺮـــﺷ ﻰﻤـــﺴﻣ ﺖﺤﺗ ﺔﻬﻛﺎﻔﻟا ﺮﺋﺎﺼﻋ ﻦﻋ ﺪﻌﺘﺑا ،ﺔﻨﺧﺎﺴﻟا ﻚﺗﺎﺑوﺮـــﺸﻣ ﻲﻓ ﺮﻜﺴﻟا ﺔﻴﻤﻛ ﻞﻠّﻗ ﺔﻬﻜﻨﻤﻟا ﺮـــﻴﻏ يدﺎﺑﺰﻟاو ﺐـــﻴﻠﺤﻟا تﺎـــﺠﺘﻨﻣ ﺮـــﺘﺧا تﺎﺠﺘﻨﻤﻠﻟ فﺎـــﻀﺗُ ﺮﻜـــﺴﻠﻟ ةﺪـــﻋ تﺎﻴﻤـــﺴﻣ ﺪـــﺟﻮﺗ .ﺔﻴﻟﺰﻨﻤﻟا تﺎﻳﻮﻠﺤﻟا داﺪﻋإ ءﺎﻨﺛأ ﺮﻜـــﺴﻟا ﺔﻴﻤﻛ ﻞﻠّﻗ دﺮﺘﺳﺎﻛ ﻲﻨﺒﻟا ﺮﻜﺴﻟا تاذ ﺔﺒﺟﻮﻟا ﺮﺘﺧا ،لﺰـــﻨﻤﻟا جرﺎﺧ مﺎﻌﻄﻟا لوﺎـــﻨﺗ ﺪﻨﻋ ةرﺬﻟا باﺮﺷ زﻮﺘﻛﻻ كرﺎﻴﺧ نﻮﻜﻳ نأ صﺮـــﺣا ﺔﻴﺋاﺬﻐﻟا رﺎـــــﻴﺘﺧا ﺪـــﻨﻋ ﻲـــﺤﺻ داﺪﻋ©ا تادﺎﺷرإ ﻊﺒﺗا قﺮـﻃ تﺎــﻤﻴﻠﻌﺗ ﻊــﺒﺗا ﻚﻟ ﺔﻴﺳﺎﺴﺤﻟا ﺐﺒﺴﺗ ﺪــﻗ ةدﺎــﻣ يأ دﻮــــﺟو مﺪـﻋ ﻦﻣ ﺪﻛﺄـﺗ دﺪﻋ هدﺪﺤﻳ ﺎﻬﺘﻟوﺎـﻨﺗ ﻲﺘﻟا",
  "text_simplified": "يحتاج الطفل النشيط إلى ممارسة النشاط البدني مثل المشي أو صعود الدرج لمدة 30 دقيقة يومياً. يجب على الأهل تشجيع الطفل على شرب الماء بدلاً من المشروبات السكرية والغازية. تجنب إضافة السكر والملح الزائد في الطعام للوقاية من السمنة وأمراض القلب. اختيار الأطعمة الطبيعية والفواكه بدلاً من الحلويات المصنعة.",
  "labels": [
    "نشاط بدني",
    "تغذية صحية",
    "وقاية من السمنة",
    "شرب الماء",
    "تقليل السكر"
  ],
  "created_at": "2026-06-21T10:36:19Z",
  "updated_at": "2026-06-21T10:36:19Z",
  "version": "1.0.0",
  "source_meta": {
    "source_title": "SFDA_Healthy_Nutrition_Guide",
    "source_author": ""
  }
}