{
  "id": "lesson_2-3_development_language_03",
  "path_id": "path_2-3_development_growth",
  "title": "التطور اللغوي والمعرفي من خلال اللعب التخيلي",
  "age_group": "2-3",
  "domain": "development",
  "unit_ids": [
    "2b2d1fdd-1a30-40f3-aa2b-0dbadea2ce2c",
    "dev-8fdf563b"
  ],
  "summary": "يتناول هذا الدرس «التطور اللغوي والمعرفي من خلال اللعب التخيلي» للأطفال من سنتين إلى ثلاث سنوات. شجعه على اللعب التخيلي؛ كأن تعطيه ملعقة ليتظاهر بإطعام دميته المحشوة، وتبادلا الأدوار في التظاهر، فهذا يطور مهارات التواصل والتفكير الرمزي لديه. دعه يلعب ببعض ملابس الكبار كالأحذية والقبعات والقمصان؛ فهذا يساعده على البدء في تمثيل الأدوار واللعب التخيلي الذي ينمي قدراته المعرفية. وفر له أشياء تحفز خياله كالأواني والمقالي ليتظاهر بالطبخ، أو مكعبات البناء. شاركه اللعب التخيلي وتحدث معه كأن تأكل الطعام الذي تظاهر بطبخه.",
  "try_this": "جرّب هذا الأسبوع: شجعه على اللعب التخيلي؛ كأن تعطيه ملعقة ليتظاهر بإطعام دميته المحشوة، وتبادلا الأدوار في التظاهر، فهذا يطور مهارات التواصل والتفكير الرمزي لديه.",
  "order": 2,
  "estimated_minutes": 5,
  "reflection_prompts": [
    "طفلي يبلغ من العمر عاماً ونصف، وأريد تطوير مهاراته اللغوية والمعرفية من خلال اللعب، كيف أبدأ؟",
    "ألاحظ أن طفلي في عمر السنتين بدأ يقلد بعض تصرفاتنا، كيف أستثمر ذلك لتعزيز خياله؟"
  ],
  "warning_flags": [],
  "is_published": true,
  "version": "1.0.0",
  "created_at": "2026-06-13T10:00:00",
  "updated_at": "2026-06-13T10:00:00"
}