{
  "title": "الرفق عند الخطأ: تأديب يبني لا يكسر — اختبار",
  "questions": [
    {
      "question": "طفلك (2-3) أخطأ وهو يستكشف. المنهج النبوي؟",
      "answerOptions": [
        {
          "text": "توجيه هادئ حازم وإبعاد عن الخطأ برفق بلا إهانة",
          "isCorrect": true,
          "rationale": "الرفق يبني والقسوة تكسر."
        },
        {
          "text": "الصراخ والضرب",
          "isCorrect": false,
          "rationale": "تعلّمه الخوف لا الفهم."
        },
        {
          "text": "تجاهل الخطأ تماماً",
          "isCorrect": false,
          "rationale": "التوجيه الهادئ مطلوب."
        }
      ],
      "hint": "حزم بلا قسوة."
    },
    {
      "question": "ما الذي يفهمه طفل 2-3 أكثر وقت التأديب؟",
      "answerOptions": [
        {
          "text": "نبرتك ووجهك أكثر من كلماتك",
          "isCorrect": true,
          "rationale": "لذا الهدوء أبلغ."
        },
        {
          "text": "شرحاً منطقياً طويلاً",
          "isCorrect": false,
          "rationale": "لا يستوعبه بعد."
        },
        {
          "text": "العقاب المؤجَّل",
          "isCorrect": false,
          "rationale": "لا يربط بينه وبين الخطأ."
        }
      ],
      "hint": "النبرة والوجه."
    },
    {
      "question": "كيف توازن بين الحزم والرفق مع طفل 2-3؟",
      "answerOptions": [
        {
          "text": "حزم في المهم برفق وبلا قسوة، ومرونة في الصغير",
          "isCorrect": true,
          "rationale": "الرفق لا يعني التسيّب."
        },
        {
          "text": "قسوة دائمة",
          "isCorrect": false,
          "rationale": "تكسر ولا تبني."
        },
        {
          "text": "تسيّب تام",
          "isCorrect": false,
          "rationale": "الحزم اللطيف مطلوب."
        }
      ],
      "hint": "حزم لطيف."
    }
  ]
}